vistal/__init__.py
vistal/timeline.py
vistal/visualization.py
vistal/subtitle/__init__.py
vistal/subtitle/elements.py
vistal/subtitle/sections.py
vistal-0.1.3.dist-info/METADATA
vistal-0.1.3.dist-info/WHEEL
vistal-0.1.3.dist-info/top_level.txt
vistal-0.1.3.dist-info/RECORD
