Metadata-Version: 2.1
Name: vistal
Version: 0.1.3
Summary: A visualization tool for temporal action localization
Home-page: https://github.com/x4Cx58x54/vistal
Author: x4Cx58x54
License: UNKNOWN
Project-URL: Homepage, https://github.com/x4Cx58x54/vistal
Project-URL: Bug Tracker, https://github.com/x4Cx58x54/vistal/issues
Keywords: visualization,temporal action localization,action segmentation,computer vision,video understanding
Platform: UNKNOWN
Classifier: Development Status :: 3 - Alpha
Classifier: Programming Language :: Python :: 3
Classifier: License :: OSI Approved :: MIT License
Classifier: Operating System :: OS Independent
Classifier: Topic :: Multimedia :: Video
Requires-Python: >=3.7
Requires-Dist: numpy
Requires-Dist: distinctipy (>=1.2.2)
